django_rest_swagger_swaggerdoc/__init__.py
django_rest_swagger_swaggerdoc/decorators.py
django_rest_swagger_swaggerdoc/documents.py
django_rest_swagger_swaggerdoc/exc.py
django_rest_swagger_swaggerdoc/renderers.py
django_rest_swagger_swaggerdoc/utils.py
django_rest_swagger_swaggerdoc/__pycache__/__init__.cpython-35.pyc
django_rest_swagger_swaggerdoc/tests/__init__.py
django_rest_swagger_swaggerdoc/tests/compat.py
django_rest_swagger_swaggerdoc/tests/settings.py
django_rest_swagger_swaggerdoc/tests/swagger_test_doc.yml
django_rest_swagger_swaggerdoc/tests/test_decorators.py
django_rest_swagger_swaggerdoc/tests/test_one.py
django_rest_swagger_swaggerdoc/tests/test_renderers.py
django_rest_swagger_swaggerdoc/tests/test_utils.py
django_rest_swagger_swaggerdoc-1.0.post3.dist-info/DESCRIPTION.rst
django_rest_swagger_swaggerdoc-1.0.post3.dist-info/METADATA
django_rest_swagger_swaggerdoc-1.0.post3.dist-info/RECORD
django_rest_swagger_swaggerdoc-1.0.post3.dist-info/WHEEL
django_rest_swagger_swaggerdoc-1.0.post3.dist-info/entry_points.txt
django_rest_swagger_swaggerdoc-1.0.post3.dist-info/metadata.json
django_rest_swagger_swaggerdoc-1.0.post3.dist-info/top_level.txt
