Metadata-Version: 2.0
Name: django-rest-swagger-swaggerdoc
Version: 1.0.post3
Summary: Inject a swagger style yaml data to the django-rest-swagger's data
Home-page: https://github.com/TakesxiSximada/django-rest-swagger-swaggerdoc
Author: TakesxiSximada
Author-email: sximada+django-rest-swagger-swaggerdoc@gmail.com
License: Apache License 2.0
Keywords: Documentation,Swagger
Platform: any
Classifier: Development Status :: 1 - Planning
Classifier: License :: OSI Approved :: Apache Software License
Classifier: Programming Language :: Python
Classifier: Programming Language :: Python :: 2
Classifier: Programming Language :: Python :: 2.7
Classifier: Programming Language :: Python :: 3
Classifier: Programming Language :: Python :: 3.4
Classifier: Programming Language :: Python :: 3.5
Classifier: Topic :: Software Development
Requires-Dist: Django
Requires-Dist: PyYAML
Requires-Dist: django-rest-swagger
Requires-Dist: djangorestframework (>=3.4.7)
Requires-Dist: six
Requires-Dist: zope.dottedname
Provides-Extra: testing
Requires-Dist: Django; extra == 'testing'
Requires-Dist: PyYAML; extra == 'testing'
Requires-Dist: coverage; extra == 'testing'
Requires-Dist: detox; extra == 'testing'
Requires-Dist: django-rest-swagger; extra == 'testing'
Requires-Dist: djangorestframework (>=3.4.7); extra == 'testing'
Requires-Dist: flake8; extra == 'testing'
Requires-Dist: mock; extra == 'testing'
Requires-Dist: pytest; extra == 'testing'
Requires-Dist: pytest-django; extra == 'testing'
Requires-Dist: six; extra == 'testing'
Requires-Dist: zope.dottedname; extra == 'testing'
